{"main_sidebar":{"search-2":{"title":""},"cocktail-recent-posts-4":{"title":"Recent Post","number":5,"show_date":true,"show_thumb":true},"archives-2":{"title":"","count":0,"dropdown":0},"categories-2":{"title":"","count":0,"hierarchical":0,"dropdown":0},"tag_cloud-2":{"title":"Tags","taxonomy":"post_tag"}},"shop_sidebar":{"woocommerce_widget_cart-2":{"title":"Cart","hide_if_empty":"1"},"woocommerce_top_rated_products-2":{"title":"Top Rated Products","number":"5"},"woocommerce_price_filter-2":{"title":"Filter by price"}},"dslc_contact":{"as_contact_info_widget-2":{"title":"CONTACT INFOMATION","name":"ALENA STUDIO","mail":"hello@alenastudio.com","phone":"+84 123 456 7890","address":"12\/34 District Phu Nhuan, Sai Gon City","xtra_info":"Suspendisse ut interdum lectus. Integer ac neque faucibus, venenatis nisl quis, pellentesque lacus. Integer et ipsum sit amet dui ultrices hendrerit. Pellentesque leo massa, suscipit a felis non, posuere convallis velit. Sed tincidunt lacinia velit et aliquam."}},"as_main_sidebar":{"search-3":{"title":""},"cocktail-recent-posts-5":{"title":"RECENT POST","number":5,"show_date":true,"show_thumb":true},"archives-3":{"title":"ARCHIVES","count":0,"dropdown":0}},"as_shop_sidebar":{"woocommerce_widget_cart-3":{"title":"Cart","hide_if_empty":"1"},"woocommerce_price_filter-3":{"title":"Filter by price"},"woocommerce_top_rated_products-3":{"title":"Top Rated Products","number":"5"}},"footer_area_1":{"text-2":{"title":"","text":"Design is not just what it looks like and feels like. Design is how it works.\r\n\r\nAenean cursus imperdiet nisl id fermentum. Aliquam pharetra dui laoreet vulputate dignissim. Sed id metus id quam auctor molestie eget ut augue.\r\n","filter":true},"as_social_info_widget-2":{"title":"","twitter":"#","facebook":"#","google_plus":"#","youtube":"#","vimeo":"","dribbble":"#","behance":"","flickr":"","tumblr":"","pinterest":"","linkedin":"","instagram":"","github":"","dropbox":"","foursquare":""}},"footer_area_2":{"cocktail-recent-posts-2":{"title":"RECENT POST","number":3,"show_date":true,"show_thumb":true}},"footer_area_3":{"tag_cloud-3":{"title":"TAGS","taxonomy":"post_tag"}},"footer_area_4":{"as_flickr_widget-2":{"title":"FLICKR PHOTOS","number":"12","flickr_id":"29210138@N04"}},"mega-menu":{"nav_menu-3":{"title":"Multi Layout","nav_menu":40,"mega_menu_columns":1,"mega_menu_parent_menu_id":1781},"nav_menu-2":{"title":"Page Custom","nav_menu":38,"mega_menu_columns":1,"mega_menu_parent_menu_id":1781},"nav_menu-4":{"title":"Portfolio Normal","nav_menu":41,"mega_menu_columns":1,"mega_menu_parent_menu_id":1782},"nav_menu-5":{"title":"Portfolio Fullwidth","nav_menu":42,"mega_menu_columns":1,"mega_menu_parent_menu_id":1782},"nav_menu-6":{"title":"Features Web","nav_menu":66,"mega_menu_columns":1,"mega_menu_parent_menu_id":1781},"nav_menu-7":{"title":"Portfolio Special","nav_menu":67,"mega_menu_columns":1,"mega_menu_parent_menu_id":1782},"blazersix-widget-image-2":{"title":"","img_url":"http:\/\/alenastudio.com\/anna\/creative\/wp-content\/uploads\/sites\/4\/2015\/05\/device-ip.png","img_title":"","link_to_web":"","mega_menu_columns":1,"mega_menu_parent_menu_id":1781},"blazersix-widget-image-3":{"title":"","img_url":"http:\/\/alenastudio.com\/anna\/creative\/wp-content\/uploads\/sites\/4\/2015\/06\/landing-2.png","img_title":"","link_to_web":"","mega_menu_columns":1,"mega_menu_parent_menu_id":1782}}}